{
"directed": false,
"multigraph": false,
"graph": {
"name": "ernet",
"demands": {},
"stats": {
"nodes": 16,
"links": 18,
"demands": 240,
"min_degree": 1,
"avg_degree": 2.25,
"std_degree": 1.56,
"max_degree": 6,
"gini": 0.36,
"min_link_len": 119.52,
"avg_link_len": 645.72,
"max_link_len": 1742.19,
"diameter_len": 3507.42,
"diameter_hops": 4,
"avg_sdp_num": 1.05,
"max_sdp_num": 2,
"avg_sdp_hops": 2.60,
"avg_sdp_len": 1820.45,
"avg_adp_num": 1.20,
"max_adp_num": 3,
"avg_adp_hops": 2.72,
"avg_adp_len": 2017.06
}
},
"nodes": [
{
"name": "Pune",
"pos": [
73.86,
18.52
],
"id": "0"
},
{
"name": "Indore",
"pos": [
75.83,
22.72
],
"id": "1"
},
{
"name": "Trivandrum",
"pos": [
76.92,
8.48
],
"id": "2"
},
{
"name": "Mumbai",
"pos": [
72.85,
19.01
],
"id": "3"
},
{
"name": "Ahmedabad",
"pos": [
72.62,
23.03
],
"id": "6"
},
{
"name": "Jaipur",
"pos": [
75.82,
26.92
],
"id": "7"
},
{
"name": "Chennai",
"pos": [
80.28,
13.09
],
"id": "20"
},
{
"name": "Bengaluru",
"pos": [
77.60,
12.98
],
"id": "21"
},
{
"name": "Delhi",
"pos": [
77.22,
28.64
],
"id": "22"
},
{
"name": "Guwahati",
"pos": [
91.75,
26.19
],
"id": "23"
},
{
"name": "Gorakhpur",
"pos": [
75.68,
29.45
],
"id": "24"
},
{
"name": "Kanpur",
"pos": [
80.35,
26.47
],
"id": "25"
},
{
"name": "Allahabad",
"pos": [
81.85,
25.45
],
"id": "26"
},
{
"name": "Kalkota",
"pos": [
88.37,
22.57
],
"id": "27"
},
{
"name": "Bhubaneswar",
"pos": [
85.83,
20.23
],
"id": "28"
},
{
"name": "Hyderabad",
"pos": [
78.47,
17.38
],
"id": "29"
}
],
"links": [
{
"dist": 119.52,
"ecmp_fwd": {
"uni": 25.64,
"deg": 26.06
},
"ecmp_bwd": {
"uni": 25.00,
"deg": 26.06
},
"source": "0",
"target": "3"
},
{
"dist": 735.51,
"ecmp_fwd": {
"uni": 32.05,
"deg": 35.69
},
"ecmp_bwd": {
"uni": 32.69,
"deg": 35.69
},
"source": "0",
"target": "21"
},
{
"dist": 515.66,
"ecmp_fwd": {
"uni": 38.46,
"deg": 19.83
},
"ecmp_bwd": {
"uni": 38.46,
"deg": 19.83
},
"source": "1",
"target": "3"
},
{
"dist": 505.33,
"ecmp_fwd": {
"uni": 38.46,
"deg": 19.83
},
"ecmp_bwd": {
"uni": 38.46,
"deg": 19.83
},
"source": "2",
"target": "21"
},
{
"dist": 1158.77,
"ecmp_fwd": {
"uni": 67.95,
"deg": 66.29
},
"ecmp_bwd": {
"uni": 67.31,
"deg": 66.29
},
"source": "3",
"target": "22"
},
{
"dist": 775.10,
"ecmp_fwd": {
"uni": 38.46,
"deg": 19.83
},
"ecmp_bwd": {
"uni": 38.46,
"deg": 19.83
},
"source": "6",
"target": "22"
},
{
"dist": 236.12,
"ecmp_fwd": {
"uni": 38.46,
"deg": 19.83
},
"ecmp_bwd": {
"uni": 38.46,
"deg": 19.83
},
"source": "7",
"target": "22"
},
{
"dist": 290.15,
"ecmp_fwd": {
"uni": 28.21,
"deg": 28.33
},
"ecmp_bwd": {
"uni": 28.21,
"deg": 28.33
},
"source": "20",
"target": "21"
},
{
"dist": 514.66,
"ecmp_fwd": {
"uni": 10.26,
"deg": 10.20
},
"ecmp_bwd": {
"uni": 10.26,
"deg": 10.20
},
"source": "20",
"target": "29"
},
{
"dist": 1742.19,
"ecmp_fwd": {
"uni": 80.13,
"deg": 100.00
},
"ecmp_bwd": {
"uni": 80.13,
"deg": 100.00
},
"source": "21",
"target": "22"
},
{
"dist": 498.14,
"ecmp_fwd": {
"uni": 28.85,
"deg": 41.64
},
"ecmp_bwd": {
"uni": 29.49,
"deg": 41.64
},
"source": "21",
"target": "29"
},
{
"dist": 391.38,
"ecmp_fwd": {
"uni": 100.00,
"deg": 87.82
},
"ecmp_bwd": {
"uni": 100.00,
"deg": 87.82
},
"source": "22",
"target": "25"
},
{
"dist": 1304.71,
"ecmp_fwd": {
"uni": 83.97,
"deg": 85.84
},
"ecmp_bwd": {
"uni": 83.33,
"deg": 85.84
},
"source": "22",
"target": "27"
},
{
"dist": 528.27,
"ecmp_fwd": {
"uni": 38.46,
"deg": 19.83
},
"ecmp_bwd": {
"uni": 38.46,
"deg": 19.83
},
"source": "23",
"target": "27"
},
{
"dist": 565.86,
"ecmp_fwd": {
"uni": 38.46,
"deg": 19.83
},
"ecmp_bwd": {
"uni": 38.46,
"deg": 19.83
},
"source": "24",
"target": "25"
},
{
"dist": 187.85,
"ecmp_fwd": {
"uni": 38.46,
"deg": 19.83
},
"ecmp_bwd": {
"uni": 38.46,
"deg": 19.83
},
"source": "25",
"target": "26"
},
{
"dist": 369.47,
"ecmp_fwd": {
"uni": 38.46,
"deg": 19.83
},
"ecmp_bwd": {
"uni": 38.46,
"deg": 19.83
},
"source": "27",
"target": "28"
},
{
"dist": 1184.27,
"ecmp_fwd": {
"uni": 35.90,
"deg": 43.34
},
"ecmp_bwd": {
"uni": 35.26,
"deg": 43.34
},
"source": "27",
"target": "29"
}
]
}